eventide/__init__.py
eventide/py.typed
eventide/_cli/__init__.py
eventide/_cli/cron.py
eventide/_cli/eventide.py
eventide/_cli/handlers.py
eventide/_cli/run.py
eventide/_cli/utils.py
eventide/_eventide/__init__.py
eventide/_eventide/config.py
eventide/_eventide/cron.py
eventide/_eventide/eventide.py
eventide/_eventide/handler.py
eventide/_eventide/hook.py
eventide/_eventide/queue.py
eventide/_eventide/worker.py
eventide/_exceptions/__init__.py
eventide/_exceptions/eventide.py
eventide/_exceptions/worker.py
eventide/_handlers/__init__.py
eventide/_handlers/handler.py
eventide/_handlers/matcher.py
eventide/_queues/__init__.py
eventide/_queues/cloudflare.py
eventide/_queues/queue.py
eventide/_queues/sqs.py
eventide/_utils/__init__.py
eventide/_utils/logging.py
eventide/_utils/pydantic.py
eventide/_utils/retry.py
eventide/_workers/__init__.py
eventide/_workers/worker.py
eventide-0.0.0a16.dist-info/METADATA
eventide-0.0.0a16.dist-info/WHEEL
eventide-0.0.0a16.dist-info/entry_points.txt
eventide-0.0.0a16.dist-info/licenses/LICENSE
eventide-0.0.0a16.dist-info/RECORD
