Metadata-Version: 2.4
Name: eventide
Version: 0.0.0a16
Summary: Fast and simple queue workers
Project-URL: homepage, https://github.com/lvieirajr/eventide
Project-URL: repository, https://github.com/lvieirajr/eventide
Project-URL: documentation, https://github.com/lvieirajr/eventide
Author-email: Luis Vieira <lvieira@lvieira.com>
Maintainer-email: Luis Vieira <lvieira@lvieira.com>
License-Expression: Apache-2.0
License-File: LICENSE
Keywords: cloudflare,cron,handler,job,message,queue,sqs,task,worker
Classifier: Development Status :: 3 - Alpha
Classifier: Intended Audience :: Developers
Classifier: License :: OSI Approved :: Apache Software License
Classifier: Operating System :: OS Independent
Classifier: Programming Language :: Python
Classifier: Programming Language :: Python :: 3
Classifier: Programming Language :: Python :: 3.9
Classifier: Programming Language :: Python :: 3.10
Classifier: Programming Language :: Python :: 3.11
Classifier: Programming Language :: Python :: 3.12
Classifier: Programming Language :: Python :: 3.13
Classifier: Topic :: Software Development :: Libraries
Classifier: Topic :: Software Development :: Libraries :: Python Modules
Classifier: Typing :: Typed
Requires-Python: <3.14,>=3.9
Requires-Dist: jmespath<2.0,>=1.0
Requires-Dist: orjson<4.0,>=3.10
Requires-Dist: pydantic-settings<3.0,>=2.3
Requires-Dist: pydantic<3.0,>=2.7
Requires-Dist: typer<0.16,>=0.12
Provides-Extra: cloudflare
Requires-Dist: cloudflare<5.0,>=3.0; extra == 'cloudflare'
Provides-Extra: core
Requires-Dist: croniter<7.0,>=6.0; extra == 'core'
Requires-Dist: watchdog<7.0,>=5.0; extra == 'core'
Provides-Extra: cron
Requires-Dist: croniter<7.0,>=6.0; extra == 'cron'
Provides-Extra: sqs
Requires-Dist: boto3<2.0,>=1.34; extra == 'sqs'
Provides-Extra: watch
Requires-Dist: watchdog<7.0,>=5.0; extra == 'watch'
